[{"name": "new-0.1-0.95", "parameters": {"size": "10x10", "start": [0, 6], "finish": [2, 5], "algo": "User", "solution episode": 1, "max_reward": 23, "difference": 5, "route_len": 4}, "image": "../database/new-0.1-0.95/img.jpg"}, {"name": "new-0.1-0.75", "parameters": {"size": "10x10", "start": [0, 6], "finish": [2, 5], "algo": "User", "solution episode": 1, "max_reward": 23, "difference": 3, "route_len": 4}, "image": "../database/new-0.1-0.75/img.jpg"}, {"name": "new-0.3-0.95", "parameters": {"size": "10x10", "start": [0, 6], "finish": [2, 5], "algo": "User", "solution episode": 1, "max_reward": 23, "difference": 3, "route_len": 4}, "image": "../database/new-0.3-0.95/img.jpg"}, {"name": "new-0.3-0.75", "parameters": {"size": "10x10", "start": [0, 6], "finish": [2, 5], "algo": "User", "solution episode": 1, "max_reward": 23, "difference": 1, "route_len": 4}, "image": "../database/new-0.3-0.75/img.jpg"}]